<?xml version="1.0" encoding="utf-8" ?><dwsync><file name="404.php" server="redtickrentals.com.au/public_html/redtickrentals/wp-content/themes/redtickrentals/" local="3449193566" remote="319519907847902800" Dst="-1" /><file name="footer.php" server="redtickrentals.com.au/public_html/redtickrentals/wp-content/themes/redtickrentals/" local="3460590420" remote="323953104376793684" Dst="-1" /><file name="form.css" server="redtickrentals.com.au/public_html/redtickrentals/wp-content/themes/redtickrentals/" local="3458801451" remote="323953104375004724" Dst="-1" /><file name="functions.php" server="redtickrentals.com.au/public_html/redtickrentals/wp-content/themes/redtickrentals/" local="3458798750" remote="323953104375001964" Dst="-1" /><file name="header.php" server="redtickrentals.com.au/public_html/redtickrentals/wp-content/themes/redtickrentals/" local="3459983934" remote="323953104376187144" Dst="-1" /><file name="index.php" server="redtickrentals.com.au/public_html/redtickrentals/wp-content/themes/redtickrentals/" local="3458855997" remote="323953104375059264" Dst="-1" /><file name="no-post.php" server="redtickrentals.com.au/public_html/redtickrentals/wp-content/themes/redtickrentals/" local="3449193531" remote="319519907847902860" Dst="-1" /><file name="page.php" server="redtickrentals.com.au/public_html/redtickrentals/wp-content/themes/redtickrentals/" local="3460348868" remote="323953104376552124" Dst="-1" /><file name="style.css" server="redtickrentals.com.au/public_html/redtickrentals/wp-content/themes/redtickrentals/" local="3460598148" remote="323953104376801364" Dst="-1" /><file name="style_text.css" server="redtickrentals.com.au/public_html/redtickrentals/wp-content/themes/redtickrentals/" local="3460590308" remote="323953104376793564" Dst="-1" /><file name="style.css" server="s173785.gridserver.com/domains/redtickrentals.com.au/html/wp-content/themes/redtickrentals/" local="3461733898" remote="3461672700" Dst="-1" /><file name="404.php" server="s173785.gridserver.com/domains/theagsc.com/html/wp-content/themes/theagsc/" local="3449193566" remote="602112512365300188" Dst="-1" /><file name="footer.php" server="s173785.gridserver.com/domains/theagsc.com/html/wp-content/themes/theagsc/" local="3464649563" remote="7759552036" Dst="-1" /><file name="form.css" server="s173785.gridserver.com/domains/theagsc.com/html/wp-content/themes/theagsc/" local="3458801451" remote="602112512365300188" Dst="-1" /><file name="functions.php" server="s173785.gridserver.com/domains/theagsc.com/html/wp-content/themes/theagsc/" local="3464634573" remote="7759537036" Dst="-1" /><file name="header.php" server="s173785.gridserver.com/domains/theagsc.com/html/wp-content/themes/theagsc/" local="3464648653" remote="7759551136" Dst="-1" /><file name="index.php" server="s173785.gridserver.com/domains/theagsc.com/html/wp-content/themes/theagsc/" local="3462099400" remote="7757005516" Dst="-1" /><file name="no-post.php" server="s173785.gridserver.com/domains/theagsc.com/html/wp-content/themes/theagsc/" local="3449193531" remote="7756974616" Dst="-1" /><file name="page.php" server="s173785.gridserver.com/domains/theagsc.com/html/wp-content/themes/theagsc/" local="3464655554" remote="7759558036" Dst="-1" /><file name="style.css" server="s173785.gridserver.com/domains/theagsc.com/html/wp-content/themes/theagsc/" local="3464655448" remote="7759557916" Dst="-1" /><file name="style_text.css" server="s173785.gridserver.com/domains/theagsc.com/html/wp-content/themes/theagsc/" local="3462076132" remote="7756982176" Dst="-1" /><file name="404.php" server="s173785.gridserver.com/domains/dvclmn.com/html/wp-content/themes/dvclmn/" local="3465985754" remote="7760924236" Dst="-1" /><file name="footer.php" server="s173785.gridserver.com/domains/dvclmn.com/html/wp-content/themes/dvclmn/" local="3465988174" remote="7760926636" Dst="-1" /><file name="form.css" server="s173785.gridserver.com/domains/dvclmn.com/html/wp-content/themes/dvclmn/" local="3458812250" remote="7760375596" Dst="-1" /><file name="functions.php" server="s173785.gridserver.com/domains/dvclmn.com/html/wp-content/themes/dvclmn/" local="3464645372" remote="7760375596" Dst="-1" /><file name="header.php" server="s173785.gridserver.com/domains/dvclmn.com/html/wp-content/themes/dvclmn/" local="3465983514" remote="7760921956" Dst="-1" /><file name="index.php" server="s173785.gridserver.com/domains/dvclmn.com/html/wp-content/themes/dvclmn/" local="3465444694" remote="7760383156" Dst="-1" /><file name="no-post.php" server="s173785.gridserver.com/domains/dvclmn.com/html/wp-content/themes/dvclmn/" local="3465985525" remote="7760923996" Dst="-1" /><file name="page.php" server="s173785.gridserver.com/domains/dvclmn.com/html/wp-content/themes/dvclmn/" local="3465977469" remote="7760915956" Dst="-1" /><file name="style.css" server="s173785.gridserver.com/domains/dvclmn.com/html/wp-content/themes/dvclmn/" local="3465991213" remote="7760929696" Dst="-1" /><file name="style_text.css" server="s173785.gridserver.com/domains/dvclmn.com/html/wp-content/themes/dvclmn/" local="3465988928" remote="7760927416" Dst="-1" /><file name="404.php" server="s173785.gridserver.com/domains/theagsc.com/html/wp-content/themes/theagsc2/" local="3465985754" remote="602446763910935512" Dst="-1" /><file name="style.css" server="s173785.gridserver.com/domains/theagsc.com/html/wp-content/themes/theagsc2/" local="3473054654" remote="7767989536" Dst="-1" /><file name="header.php" server="s173785.gridserver.com/domains/theagsc.com/html/wp-content/themes/theagsc2/" local="3472901081" remote="7767835936" Dst="-1" /><file name="page.php" server="s173785.gridserver.com/domains/theagsc.com/html/wp-content/themes/theagsc2/" local="3472891214" remote="7767826096" Dst="-1" /><file name="style_text.css" server="s173785.gridserver.com/domains/theagsc.com/html/wp-content/themes/theagsc2/" local="3472836917" remote="7767771796" Dst="-1" /><file name="footer.php" server="s173785.gridserver.com/domains/theagsc.com/html/wp-content/themes/theagsc2/" local="3473054160" remote="7767989056" Dst="-1" /><file name="functions.php" server="s173785.gridserver.com/domains/theagsc.com/html/wp-content/themes/theagsc2/" local="3466858547" remote="602446763910935512" Dst="-1" /><file name="index.php" server="s173785.gridserver.com/domains/theagsc.com/html/wp-content/themes/theagsc2/" local="3472901193" remote="7767836056" Dst="-1" /><file name="form.css" server="s173785.gridserver.com/domains/theagsc.com/html/wp-content/themes/theagsc2/" local="3473054228" remote="7767989116" Dst="-1" /><file name="no-post.php" server="s173785.gridserver.com/domains/theagsc.com/html/wp-content/themes/theagsc2/" local="3465985525" remote="7767765976" Dst="-1" /><file name="404.php" server="s173785.gridserver.com/domains/newsite.theagsc.com/html/wp-content/themes/theagsc/" local="3465985754" remote="602446763912056372" Dst="-1" /><file name="footer.php" server="s173785.gridserver.com/domains/newsite.theagsc.com/html/wp-content/themes/theagsc/" local="3474262252" remote="7769197096" Dst="-1" /><file name="form.css" server="s173785.gridserver.com/domains/newsite.theagsc.com/html/wp-content/themes/theagsc/" local="3474223457" remote="7769158336" Dst="-1" /><file name="functions.php" server="s173785.gridserver.com/domains/newsite.theagsc.com/html/wp-content/themes/theagsc/" local="3474207087" remote="7769141956" Dst="-1" /><file name="header.php" server="s173785.gridserver.com/domains/newsite.theagsc.com/html/wp-content/themes/theagsc/" local="3474261692" remote="7769196556" Dst="-1" /><file name="index.php" server="s173785.gridserver.com/domains/newsite.theagsc.com/html/wp-content/themes/theagsc/" local="3474208526" remote="7769143396" Dst="-1" /><file name="no-post.php" server="s173785.gridserver.com/domains/newsite.theagsc.com/html/wp-content/themes/theagsc/" local="3465985525" remote="7768886956" Dst="-1" /><file name="page.php" server="s173785.gridserver.com/domains/newsite.theagsc.com/html/wp-content/themes/theagsc/" local="3474198617" remote="7769133496" Dst="-1" /><file name="style.css" server="s173785.gridserver.com/domains/newsite.theagsc.com/html/wp-content/themes/theagsc/" local="3474981370" remote="7769916256" Dst="-1" /><file name="style_text.css" server="s173785.gridserver.com/domains/newsite.theagsc.com/html/wp-content/themes/theagsc/" local="3474301343" remote="7769236216" Dst="-1" /><file name="search.php" server="s173785.gridserver.com/domains/newsite.theagsc.com/html/wp-content/themes/theagsc/" local="3474117898" remote="7769052736" Dst="-1" /><file name="post-search.php" server="s173785.gridserver.com/domains/newsite.theagsc.com/html/wp-content/themes/theagsc/" local="3474021581" remote="602446763912125972" Dst="-1" /><file name="content-aside.php" server="s173785.gridserver.com/domains/newsite.theagsc.com/html/wp-content/themes/theagsc/" local="3469705208" remote="602446763912128732" Dst="-1" /><file name="content-audio.php" server="s173785.gridserver.com/domains/newsite.theagsc.com/html/wp-content/themes/theagsc/" local="3469705208" remote="602446763912128732" Dst="-1" /><file name="content-featured-post.php" server="s173785.gridserver.com/domains/newsite.theagsc.com/html/wp-content/themes/theagsc/" local="3469705208" remote="602446763912128732" Dst="-1" /><file name="content-gallery.php" server="s173785.gridserver.com/domains/newsite.theagsc.com/html/wp-content/themes/theagsc/" local="3469705208" remote="602446763912128732" Dst="-1" /><file name="content-image.php" server="s173785.gridserver.com/domains/newsite.theagsc.com/html/wp-content/themes/theagsc/" local="3469705208" remote="602446763912128732" Dst="-1" /><file name="content-link.php" server="s173785.gridserver.com/domains/newsite.theagsc.com/html/wp-content/themes/theagsc/" local="3469705208" remote="602446763912128732" Dst="-1" /><file name="content-none.php" server="s173785.gridserver.com/domains/newsite.theagsc.com/html/wp-content/themes/theagsc/" local="3469705208" remote="602446763912128732" Dst="-1" /><file name="content-page.php" server="s173785.gridserver.com/domains/newsite.theagsc.com/html/wp-content/themes/theagsc/" local="3469705208" remote="602446763912128732" Dst="-1" /><file name="content-quote.php" server="s173785.gridserver.com/domains/newsite.theagsc.com/html/wp-content/themes/theagsc/" local="3469705208" remote="602446763912128732" Dst="-1" /><file name="content-video.php" server="s173785.gridserver.com/domains/newsite.theagsc.com/html/wp-content/themes/theagsc/" local="3469705208" remote="602446763912128732" Dst="-1" /><file name="content.php" server="s173785.gridserver.com/domains/newsite.theagsc.com/html/wp-content/themes/theagsc/" local="3469705208" remote="602446763912128732" Dst="-1" /><file name="503.php" server="s173785.gridserver.com/domains/newsite.theagsc.com/html/wp-content/themes/theagsc/" local="3474175122" remote="602446763912279512" Dst="-1" /><file name="fonts.css" server="s173785.gridserver.com/domains/newsite.theagsc.com/html/wp-content/themes/theagsc/" local="3474222655" remote="7769157496" Dst="-1" /><file name="category.php" server="s173785.gridserver.com/domains/newsite.theagsc.com/html/wp-content/themes/theagsc/" local="3474208679" remote="7769143576" Dst="-1" /><file name="sidebar.css" server="s173785.gridserver.com/domains/newsite.theagsc.com/html/wp-content/themes/theagsc/" local="3474218062" remote="7769152936" Dst="-1" /><file name="sidebar.php" server="s173785.gridserver.com/domains/newsite.theagsc.com/html/wp-content/themes/theagsc/" local="3474357811" remote="7769292676" Dst="-1" /></dwsync>